[{"name": "flicket_admin", "password": "$2b$12$P2AmHDaLvnkZXZ5hsCGtOulSpournXrucDk81of8Cu9GUPRi97vtG", "email": "evereux@gmail.com", "username": "flicket_admin"}, {"name": "announcer", "password": "$2b$12$VP3/fbSWzvKcEfs1y3auUuu1sS44v2e0gpfP6WXKrto2nWW1lPxTq", "email": "flicket_admin@localhost.com", "username": "announcer"}, {"name": "Eliana Kip", "password": "$2b$12$kEwjXEVcLHm6QLb0fFkM6efFMYZAexVqQDF/EoEfH25SXvFzNIemW", "email": "elianakip+evereux@gmail.com", "username": "elianakip"}, {"name": "Quinn Ladonna", "password": "$2b$12$cb/v9bRy84R/Qt/4VSjeyu27vYFuW/ZcVeNJcik1uoMELJ6QZxSpW", "email": "quinnladonna+evereux@gmail.com", "username": "quinnladonna"}, {"name": "Judith Rene", "password": "$2b$12$a9E2wCHIkNlt8.HGa2Gvuutx3vpICWUhtxsb1zGKFDEM9EWxkyuXK", "email": "judithrene+evereux@gmail.com", "username": "judithrene"}, {"name": "Kathy Phil", "password": "$2b$12$EhaDUZWXuXcykk95onla..Eh7JKQw4VhEFXFVZIRarmOmH6KCBi2e", "email": "kathyphil+evereux@gmail.com", "username": "kathyphil"}, {"name": "Morris Precious", "password": "$2b$12$gESrAOekb3oy4TS7Ypi3EO7ogtc9Kfh4uK.lMR7FzjfAHtfG5oViu", "email": "morrisprecious+evereux@gmail.com", "username": "morrisprecious"}, {"name": "Alisha Elisabeth", "password": "$2b$12$HjTaGPXCFULRKU8kQWUmq.Uqo0OMjzaC5R/MAE1Auzjht4wat7K9.", "email": "alishaelisabeth+evereux@gmail.com", "username": "alishaelisabeth"}, {"name": "Faye Jaylin", "password": "$2b$12$mTd9Za9bb5ry0grxuO37WOJmlt3EbWfVjrQzBJEtLjwir17ruEVPm", "email": "fayejaylin+evereux@gmail.com", "username": "fayejaylin"}, {"name": "Peyton Nesbit", "password": "$2b$12$ikGStwWug.zG7lGEuCkAg.TeeKYh8NY/Y/7bw23hR5YknEdoZIety", "email": "peytonnesbit+evereux@gmail.com", "username": "peytonnesbit"}, {"name": "Shawn Miles", "password": "$2b$12$jTf/9QGhtrZe.zl1E7fp/.f/oPkpaa2uheCi2VA9uvT0yDOvgi/9C", "email": "shawnmiles+evereux@gmail.com", "username": "shawnmiles"}, {"name": "Kerry Lloyd", "password": "$2b$12$poTN/uHOtfUIb0tP5l3MZuiWFb5CjYcFfkMg/k8aM4PniclpSsuxK", "email": "kerrylloyd+evereux@gmail.com", "username": "kerrylloyd"}, {"name": "Eliana Carl", "password": "$2b$12$fGWemq/UggbBB/0rUZ2xAOdSlQEtztvjyESqLHRg3ywusqw.Hlv6y", "email": "elianacarl+evereux@gmail.com", "username": "elianacarl"}, {"name": "Tiana Roy", "password": "$2b$12$wSfeeu/PCz2HT4Gp2OdGoeD65YhznLrVPm2i5nvUp0xfIURo2ZaJS", "email": "tianaroy+evereux@gmail.com", "username": "tianaroy"}, {"name": "Ryland Kristian", "password": "$2b$12$48g.GiY3lisiyRbpzrxRBOYdlyIununSmAnVSlb9g8YicJK.JU18.", "email": "rylandkristian+evereux@gmail.com", "username": "rylandkristian"}, {"name": "Cory Kristian", "password": "$2b$12$YcptTXr83MPIOJyeBK9ZoeE4BE1.2Lf7u73.ckxyaWPzHinBtyPzS", "email": "corykristian+evereux@gmail.com", "username": "corykristian"}, {"name": "Forrest Daniella", "password": "$2b$12$.OtqMLvJnrfVspxEEHW.IOyXmYv8toOJOOp.HkDK.aPyt6/YYIRNm", "email": "forrestdaniella+evereux@gmail.com", "username": "forrestdaniella"}, {"name": "Kenny Leticia", "password": "$2b$12$ybXwk59/Dmmk/j0jTjBHvOUQhjnC9ny8rx0EBXhm.fuxFxEXsqtiK", "email": "kennyleticia+evereux@gmail.com", "username": "kennyleticia"}, {"name": "Louie Cathal", "password": "$2b$12$hUUSQYFeqaFyF/5B6vNqKOTF3.CKTQ8k7iX3Ra6JmiGh21EjcQ4/G", "email": "louiecathal+evereux@gmail.com", "username": "louiecathal"}, {"name": "Jacqueline Kaylie", "password": "$2b$12$lKnRjhX7KrjXs5xBWHD1HuogwDXlzPSbgCmKKJ09C74.hrkgG9IkW", "email": "jacquelinekaylie+evereux@gmail.com", "username": "jacquelinekaylie"}, {"name": "Jeannette Lavana", "password": "$2b$12$CcWJdPp4zNup0mfCrxIQtuRT0pQvyaFp9OxpC1Iaq/IETPMDJdOfO", "email": "jeannettelavana+evereux@gmail.com", "username": "jeannettelavana"}, {"name": "Elaine Liza", "password": "$2b$12$J9bSHm03wo0Y9l.8JuTXZetkqsUkGYRTtbqORyTijvN7X0DGnk.vy", "email": "elaineliza+evereux@gmail.com", "username": "elaineliza"}, {"name": "Conor Blaine", "password": "$2b$12$r/nKG23H0L4RoikMXNlBz.8wf1OnNdwd9CBT4UMZUOqE4ie2i0QBi", "email": "conorblaine+evereux@gmail.com", "username": "conorblaine"}, {"name": "Christie Margie", "password": "$2b$12$dAgEQ0lBwVgp7n6y0GTI.uEHzfCn4vQ/qDmBIoU.4e33zH6/bv.H.", "email": "christiemargie+evereux@gmail.com", "username": "christiemargie"}, {"name": "Marie Caoimhe", "password": "$2b$12$FR/2loB0g993qEJE0u0Z0ejYc8oKzoazgH/4b84f.5tRx/KqeRrBG", "email": "mariecaoimhe+evereux@gmail.com", "username": "mariecaoimhe"}, {"name": "Rod Demetrius", "password": "$2b$12$/k063Ib23p8lmQmhazyb2OnRwkElS4wCQz7GRedFsbJD8hrxlgCJ.", "email": "roddemetrius+evereux@gmail.com", "username": "roddemetrius"}, {"name": "Bertha Addison", "password": "$2b$12$OZfpK1H2D8Ke/9.X/PBuyOapaRvwF/ZdhL2vjhQpCv0ziluadB97e", "email": "berthaaddison+evereux@gmail.com", "username": "berthaaddison"}, {"name": "Janine Warren", "password": "$2b$12$sFdGbKko4xV77.ivPvIQ3.OwSC6TCoRtt2w9T/GPIwyc5lCVzNstu", "email": "janinewarren+evereux@gmail.com", "username": "janinewarren"}, {"name": "Peter Andrea", "password": "$2b$12$T.7BPXfhLoFYF1vCMezrU.kjzcObHbHOThKxYV8LuMjqDsq00nrky", "email": "peterandrea+evereux@gmail.com", "username": "peterandrea"}, {"name": "Kelli Jeannette", "password": "$2b$12$OKw60ZpMzVegxklZqDkHTu1JT8kqeCXYIpsyqumssmbawOi7DQd1S", "email": "kellijeannette+evereux@gmail.com", "username": "kellijeannette"}, {"name": "Elaina Eoghan", "password": "$2b$12$9jF7afKxbzRx9XP.Wyzr8e4aLwYjI0ROlnhCYbwbdPGSfMxSSx2x.", "email": "elainaeoghan+evereux@gmail.com", "username": "elainaeoghan"}, {"name": "Kenny Alan", "password": "$2b$12$HPXDzg6HmYSvCd0OL4MgfemEFnGhTWJ8X8yLS8mXNTc9FGWOmi0CW", "email": "kennyalan+evereux@gmail.com", "username": "kennyalan"}, {"name": "Blaine Yolanda", "password": "$2b$12$qybaYtXGgBE7n10F27BrPOjB4C8DRJKY8pjPNCqeur4Harja1Gyje", "email": "blaineyolanda+evereux@gmail.com", "username": "blaineyolanda"}, {"name": "Giovanni Oliver", "password": "$2b$12$32oewwnnh56W57YwG//NbuZMB6YwVac/3/qrPT6LnMCovSxOmGSgy", "email": "giovannioliver+evereux@gmail.com", "username": "giovannioliver"}, {"name": "Gretchen Caoimhe", "password": "$2b$12$WtaeqY7T6AHj4jxbHHicf.f4G6Tlgpzh5Vv43KK2wTJAQsnaIr1BC", "email": "gretchencaoimhe+evereux@gmail.com", "username": "gretchencaoimhe"}, {"name": "Lorrie Vihan", "password": "$2b$12$fYw8MF1eqDeVEnH7qYsPDe8S5GCPtKHVX.RjGMlqFwsNa7g2Jx74K", "email": "lorrievihan+evereux@gmail.com", "username": "lorrievihan"}, {"name": "Cynthia Teddy", "password": "$2b$12$KdlpCi37PRJwYYsue1lda.5c7sQlXNxg6kb0KIGPnAnSu6/n9jXIq", "email": "cynthiateddy+evereux@gmail.com", "username": "cynthiateddy"}, {"name": "Lynda Steven", "password": "$2b$12$qlYtYOPx2oHAFS9lmua3BOayB4aDZXhfaO9hHYvB0iGoiaE8HxaLe", "email": "lyndasteven+evereux@gmail.com", "username": "lyndasteven"}, {"name": "Shauna Stacy", "password": "$2b$12$Dn7K0t2LQRO3erfZVA1Mm.dfs1QvEeVVeozWe936WDncvGqWgBjQO", "email": "shaunastacy+evereux@gmail.com", "username": "shaunastacy"}, {"name": "Clinton Janie", "password": "$2b$12$DjTo/ZqgveriWAIorZ/USu10OAyIvRcvtgU1FdwPzXNBP1XzknFdO", "email": "clintonjanie+evereux@gmail.com", "username": "clintonjanie"}, {"name": "Lamont Reynaldo", "password": "$2b$12$e43GaRmOm4LFuThRdeuxfuWqSmtyUH19PE.5Z4ej.aW6hh88EqNAu", "email": "lamontreynaldo+evereux@gmail.com", "username": "lamontreynaldo"}, {"name": "Patti Jillian", "password": "$2b$12$WSGDXh6vaj5UwC9wpHGfN.J2dCJ4KmztEEQQq1uBF2dHUFBCayGU6", "email": "pattijillian+evereux@gmail.com", "username": "pattijillian"}, {"name": "Jonathan Oran", "password": "$2b$12$A00d7bHRtrOdOKjo2kWdrOciYNx6bOZeCSCOLc40m2ppquMGCo9KC", "email": "jonathanoran+evereux@gmail.com", "username": "jonathanoran"}, {"name": "Rene Stephanie", "password": "$2b$12$2gP4R8Q.p.t4/D9DcRh.AO8ue.fcW6CDRKz8i9T9zemA5zU4O3FNK", "email": "renestephanie+evereux@gmail.com", "username": "renestephanie"}, {"name": "Alexis Damian", "password": "$2b$12$N2nDGksLHyJNipdXG4ayyeraciiL33u4RGwOYeftu7EiFYAjhuQJy", "email": "alexisdamian+evereux@gmail.com", "username": "alexisdamian"}, {"name": "Marybeth Christi", "password": "$2b$12$HvOlPLtFjiMfg2q/guIVquKxL3Xt5aeubiBpBhiXF1zuKc/E4WUsG", "email": "marybethchristi+evereux@gmail.com", "username": "marybethchristi"}, {"name": "Kerry Spencer", "password": "$2b$12$J6NvWxC4rGJjaKEgOnDpmebRzHzpZbENntxwGyFR.VPVmEx1QXpgC", "email": "kerryspencer+evereux@gmail.com", "username": "kerryspencer"}, {"name": "Laurence Jadon", "password": "$2b$12$T4gzRh0OZwYTGyiXHCB8RubRlOyNb.e6vUAVL9eatKruQZTTLdu5S", "email": "laurencejadon+evereux@gmail.com", "username": "laurencejadon"}, {"name": "Darcy Leilani", "password": "$2b$12$LlZ.3ovHOhv.3n0k0CpZOeqw1LoXVLt1yAGld41mCxJ5kCRuKAUUu", "email": "darcyleilani+evereux@gmail.com", "username": "darcyleilani"}, {"name": "Kamryn Zak", "password": "$2b$12$cuBg7yVFooMuNE32wZVftejOQmetiJwZHl324tIFW6Fjt.rP4QOx.", "email": "kamrynzak+evereux@gmail.com", "username": "kamrynzak"}, {"name": "Paul Bourne", "password": "$2b$12$wTbs88VCWUZKe7wm/N0HZeos4W5zuWCWBI1Qb8wJJE3P3jO6aEzS6", "email": "pbourne@avs-sys.com", "username": "admin"}, {"name": "Claire Tovee", "password": "$2b$12$sKQKqeg5TOPEBaL2irrSX.YBctjNRPk2HeUjofutSZM0VdO.K1jbS", "email": "ctovee@avs-sys.com", "username": "ctovee"}, {"name": "Paul Bourne 2", "password": "$2b$12$KJt5WJKsLxsHhfQ8V1BbyeVlzkCCSJ2BDWMINHZF6EsPO1XPkE4Ne", "email": "pbourne2@avs-sys.com", "username": "pbourne"}]